rengine/__init__.py
rengine/config.py
rengine/config_proxy.py
rengine/data_structures.py
rengine/dataset.py
rengine/exercises.py
rengine/workout_plan.py
rengine/workouts.py
rengine/data/__init__.py
rengine/data/clean_data.csv
rengine/data/exercises.xlsx
rengine/data/test.csv
rengine/scripts/__init__.py
rengine/scripts/generate_exercise.py
rengine/scripts/generate_workout_plan.py
rengine_workouts-1.0.14.dist-info/LICENSE
rengine_workouts-1.0.14.dist-info/METADATA
rengine_workouts-1.0.14.dist-info/WHEEL
rengine_workouts-1.0.14.dist-info/entry_points.txt
rengine_workouts-1.0.14.dist-info/top_level.txt
rengine_workouts-1.0.14.dist-info/RECORD
