Metadata-Version: 2.1
Name: rengine-workouts
Version: 1.0.14
Summary: Tools to generate workouts
Home-page: https://github.com/noahsolomon0518/rengine
Author: noahsolomon0518
Author-email: noahsolomon0518@gmail.com
License: MIT
Platform: UNKNOWN
Classifier: License :: OSI Approved :: MIT License
License-File: LICENSE
Requires-Dist: pandas
Requires-Dist: numpy
Requires-Dist: dataframe-image
Requires-Dist: openpyxl
